levelz/__init__.py
levelz/block.py
levelz/builder.py
levelz/coord.py
levelz/level.py
levelz/matrix.py
levelz/parser.py
levelz-0.1.1.dist-info/METADATA
levelz-0.1.1.dist-info/WHEEL
levelz-0.1.1.dist-info/licenses/LICENSE
levelz-0.1.1.dist-info/RECORD
