Metadata-Version: 2.3
Name: levelz
Version: 0.1.1
Summary: Python bindings for the LevelZ File Format
Project-URL: Homepage, https://github.com/LevelZ-File/py-bindings
Project-URL: Issues, https://github.com/LevelZ-File/py-bindings/issues/new/choose
Author: Calculus Games
License-File: LICENSE
Classifier: License :: OSI Approved :: MIT License
Classifier: Programming Language :: Python :: 3
Requires-Python: >=3.4
